KiemTraTrenLop/LIFOandFIFO/SourceCode/LIFO/LIFO.v
module LIFO (
    input wire clk,          // Clock signal
    input wire rst,          // Reset signal
    input wire w_en,         // Write (push) enable
    input wire r_en,         // Read (pop) enable
    input wire [31:0] data_in,  // Data input
    output reg [31:0] data_out, // Data output
    output wire full,        // Stack full indicator
    output wire empty        // Stack empty indicator
);

// Memory array declaration
reg [31:0] stack_mem [31:0]; // 32x32 memory array (depth=32, width=32)

// Stack pointer declaration (6-bit to handle 0-32 states)
reg [5:0] sp;                // Points to next available space

// Status flags assignments
assign full = (sp == 6'd32); // Full when pointer reaches 32
assign empty = (sp == 6'd0); // Empty when pointer is 0

// Stack control logic
always @(posedge clk) begin
    if (rst) begin           // Synchronous reset
        sp <= 6'd0;
        data_out <= 32'bz;   // High-impedance when reset
    end
    else begin
        // Push operation (highest priority)
        if (w_en && !full) begin
            stack_mem[sp] <= data_in;  // Store data at current pointer
            sp <= sp + 1;             // Increment stack pointer
        end
        
        // Pop operation (only if not pushing)
        else if (r_en && !empty) begin
            sp <= sp - 1;             // Decrement pointer first
            data_out <= stack_mem[sp - 1]; // Read previous top element
        end
        
        // Maintain output when no operations
        else begin
            data_out <= data_out;     // Keep previous value
        end
    end
end

endmodule

KiemTraTrenLop/LIFOandFIFO/SourceCode/LIFO/TB.v
`timescale 1ns/100ps

module TB;
    // Parameters
    parameter CLK_PERIOD = 10; // 10ns clock period (100MHz)
    
    // Signals for DUT
    reg clk;
    reg rst;
    reg w_en;
    reg r_en;
    reg [31:0] data_in;
    wire [31:0] data_out;
    wire full;
    wire empty;
    
    // Instantiate the DUT (Design Under Test)
    LIFO dut (
        .clk(clk),
        .rst(rst),
        .w_en(w_en),
        .r_en(r_en),
        .data_in(data_in),
        .data_out(data_out),
        .full(full),
        .empty(empty)
    );
    
    // Clock generation
    always begin
        clk = 0;
        #(CLK_PERIOD/2);
        clk = 1;
        #(CLK_PERIOD/2);
    end
    
    // Test vector counter and error tracking
    integer test_count = 0;
    integer error_count = 0;
    
    // Task for driving signals and checking results
    task check_lifo;
        input [31:0] write_data;
        input write_en;
        input read_en;
        input expected_full;
        input expected_empty;
        input [31:0] expected_data;
        input check_data;
        begin
            test_count = test_count + 1;
            
            // Drive inputs
            @(posedge clk);
            #1; // Small delay after clock edge
            w_en = write_en;
            r_en = read_en;
            data_in = write_data;
            
            // Wait for next clock and check outputs
            @(posedge clk);
            #1; // Small delay for outputs to stabilize
            
            // Check flags
            if (full !== expected_full) begin
                $display("ERROR at test %0d: full = %b, expected = %b", test_count, full, expected_full);
                error_count = error_count + 1;
            end
            
            if (empty !== expected_empty) begin
                $display("ERROR at test %0d: empty = %b, expected = %b", test_count, empty, expected_empty);
                error_count = error_count + 1;
            end
            
            // Check data output if needed
            if (check_data == 1 && data_out !== expected_data) begin
                $display("ERROR at test %0d: data_out = %h, expected = %h", test_count, data_out, expected_data);
                error_count = error_count + 1;
            end
            
            // Debug info
            $display("Test %0d: w_en=%b, r_en=%b, data_in=%h, data_out=%h, full=%b, empty=%b", 
                     test_count, write_en, read_en, write_data, data_out, full, empty);
        end
    endtask
    
    // Array to store test data
    reg [31:0] test_data [0:31];
    integer i;
    
    // Main test sequence
    initial begin
        // Initialize test data array with unique values
        for (i = 0; i < 32; i = i + 1) begin
            test_data[i] = 32'hB0000000 + i;
        end
        
        // Initialize signals
        rst = 0;
        w_en = 0;
        r_en = 0;
        data_in = 0;
        
        // Apply reset
        #(CLK_PERIOD*2);
        rst = 1;
        #(CLK_PERIOD*2);
        rst = 0;
        #(CLK_PERIOD);
        
        // Test 1: Check initial conditions after reset
        check_lifo(32'h0, 0, 0, 0, 1, 32'hz, 0);
        
        // Test 2: Push single data
        check_lifo(test_data[0], 1, 0, 0, 0, 32'hz, 0);
        
        // Test 3: Pop single data (should get the same value back)
        check_lifo(32'h0, 0, 1, 0, 1, test_data[0], 1);
        
        // Test 4: Push multiple data in sequence
        for (i = 0; i < 5; i = i + 1) begin
            check_lifo(test_data[i], 1, 0, 0, 0, 32'hz, 0);
        end
        
        // Test 5: Pop multiple data in reverse order (LIFO behavior)
        for (i = 4; i >= 0; i = i - 1) begin
            check_lifo(32'h0, 0, 1, 0, (i==0), test_data[i], 1);
        end
        
        // Test 6: Fill the stack to check full flag
        for (i = 0; i < 32; i = i + 1) begin
            check_lifo(test_data[i], 1, 0, (i==31), 0, 32'hz, 0);
        end
        
        // Test 7: Try to push when full (should not change stack state)
        check_lifo(32'hFFFFFFFF, 1, 0, 1, 0, 32'hz, 0);
        
        // Test 8: Pop all data in reverse order and verify
        for (i = 31; i >= 0; i = i - 1) begin
            check_lifo(32'h0, 0, 1, 0, (i==0), test_data[i], 1);
        end
        
        // Test 9: Try to pop from empty stack
        check_lifo(32'h0, 0, 1, 0, 1, 32'hz, 0);
        
        // Test 10: Test push priority over pop (push and pop simultaneously)
        // Push some data first
        for (i = 0; i < 3; i = i + 1) begin
            check_lifo(test_data[i], 1, 0, 0, 0, 32'hz, 0);
        end
        
        // Now try simultaneous push and pop (push should win)
        check_lifo(test_data[10], 1, 1, 0, 0, 32'hz, 0);
        
        // Verify the push happened by popping values
        check_lifo(32'h0, 0, 1, 0, 0, test_data[10], 1); // First pop gets recently pushed value
        for (i = 2; i >= 0; i = i - 1) begin
            check_lifo(32'h0, 0, 1, 0, (i==0), test_data[i], 1);
        end
        
        // Display test results
        if (error_count == 0)
            $display("All %0d tests PASSED!", test_count);
        else
            $display("%0d out of %0d tests FAILED!", error_count, test_count);
            
        #(CLK_PERIOD*5);
        $finish;
    end
    
    // Optional waveform dump for viewing in a waveform viewer
    initial begin
        $dumpfile("lifo_tb.vcd");
        $dumpvars(0, TB);
    end
    
endmodule

KiemTraTrenLop/LIFOandFIFO/SourceCode/LIFO/simulation/modelsim/lifo_tb.vcd
$date
	Mon Apr 14 14:51:13 2025
$end
$version
	ModelSim Version 10.5b
$end
$timescale
	1ps
$end

$scope module TB $end
$var parameter 32 ! CLK_PERIOD $end
$var reg 1 " clk $end
$var reg 1 # rst $end
$var reg 1 $ w_en $end
$var reg 1 % r_en $end
$var reg 32 & data_in [31:0] $end
$var wire 1 ' data_out [31] $end
$var wire 1 ( data_out [30] $end
$var wire 1 ) data_out [29] $end
$var wire 1 * data_out [28] $end
$var wire 1 + data_out [27] $end
$var wire 1 , data_out [26] $end
$var wire 1 - data_out [25] $end
$var wire 1 . data_out [24] $end
$var wire 1 / data_out [23] $end
$var wire 1 0 data_out [22] $end
$var wire 1 1 data_out [21] $end
$var wire 1 2 data_out [20] $end
$var wire 1 3 data_out [19] $end
$var wire 1 4 data_out [18] $end
$var wire 1 5 data_out [17] $end
$var wire 1 6 data_out [16] $end
$var wire 1 7 data_out [15] $end
$var wire 1 8 data_out [14] $end
$var wire 1 9 data_out [13] $end
$var wire 1 : data_out [12] $end
$var wire 1 ; data_out [11] $end
$var wire 1 < data_out [10] $end
$var wire 1 = data_out [9] $end
$var wire 1 > data_out [8] $end
$var wire 1 ? data_out [7] $end
$var wire 1 @ data_out [6] $end
$var wire 1 A data_out [5] $end
$var wire 1 B data_out [4] $end
$var wire 1 C data_out [3] $end
$var wire 1 D data_out [2] $end
$var wire 1 E data_out [1] $end
$var wire 1 F data_out [0] $end
$var wire 1 G full $end
$var wire 1 H empty $end
$var integer 32 I test_count $end
$var integer 32 J error_count $end
$var integer 32 K i $end

$scope task check_lifo $end
$var reg 32 L write_data [31:0] $end
$var reg 1 M write_en $end
$var reg 1 N read_en $end
$var reg 1 O expected_full $end
$var reg 1 P expected_empty $end
$var reg 32 Q expected_data [31:0] $end
$var reg 1 R check_data $end
$upscope $end

$scope module dut $end
$var wire 1 S clk $end
$var wire 1 T rst $end
$var wire 1 U w_en $end
$var wire 1 V r_en $end
$var wire 1 W data_in [31] $end
$var wire 1 X data_in [30] $end
$var wire 1 Y data_in [29] $end
$var wire 1 Z data_in [28] $end
$var wire 1 [ data_in [27] $end
$var wire 1 \ data_in [26] $end
$var wire 1 ] data_in [25] $end
$var wire 1 ^ data_in [24] $end
$var wire 1 _ data_in [23] $end
$var wire 1 ` data_in [22] $end
$var wire 1 a data_in [21] $end
$var wire 1 b data_in [20] $end
$var wire 1 c data_in [19] $end
$var wire 1 d data_in [18] $end
$var wire 1 e data_in [17] $end
$var wire 1 f data_in [16] $end
$var wire 1 g data_in [15] $end
$var wire 1 h data_in [14] $end
$var wire 1 i data_in [13] $end
$var wire 1 j data_in [12] $end
$var wire 1 k data_in [11] $end
$var wire 1 l data_in [10] $end
$var wire 1 m data_in [9] $end
$var wire 1 n data_in [8] $end
$var wire 1 o data_in [7] $end
$var wire 1 p data_in [6] $end
$var wire 1 q data_in [5] $end
$var wire 1 r data_in [4] $end
$var wire 1 s data_in [3] $end
$var wire 1 t data_in [2] $end
$var wire 1 u data_in [1] $end
$var wire 1 v data_in [0] $end
$var reg 32 w data_out [31:0] $end
$var wire 1 G full $end
$var wire 1 H empty $end
$var reg 6 x sp [5:0] $end
$upscope $end
$upscope $end
$enddefinitions $end
#0
$dumpvars
0"
0#
0$
0%
b0 &
bx w
bx x
bx L
xM
xN
xO
xP
bx Q
xR
b1010 !
b0 I
b0 J
b100000 K
xF
xE
xD
xC
xB
xA
x@
x?
x>
x=
x<
x;
x:
x9
x8
x7
x6
x5
x4
x3
x2
x1
x0
x/
x.
x-
x,
x+
x*
x)
x(
x'
xG
xH
0v
0u
0t
0s
0r
0q
0p
0o
0n
0m
0l
0k
0j
0i
0h
0g
0f
0e
0d
0c
0b
0a
0`
0_
0^
0]
0\
0[
0Z
0Y
0X
0W
0V
0U
0T
0S
$end
#5000
1"
1S
#10000
0"
0S
#15000
1"
1S
#20000
1#
0"
1T
0S
#25000
1"
1S
b0 x
bz w
1H
0G
zF
zE
zD
zC
zB
zA
z@
z?
z>
z=
z<
z;
z:
z9
z8
z7
z6
z5
z4
z3
z2
z1
z0
z/
z.
z-
z,
z+
z*
z)
z(
z'
#30000
0"
0S
#35000
1"
1S
#40000
0#
0"
0T
0S
#45000
1"
1S
#50000
b0 L
0M
0N
0O
1P
bz Q
0R
b1 I
0"
0S
#55000
1"
1S
#60000
0"
0S
#65000
1"
1S
#66000
b10110000000000000000000000000000 L
1M
0P
b10 I
#70000
0"
0S
#75000
1"
1S
#76000
1$
b10110000000000000000000000000000 &
1U
1Z
1Y
1W
#80000
0"
0S
#85000
1"
1S
b1 x
0H
#86000
b0 L
0M
1N
1P
b10110000000000000000000000000000 Q
1R
b11 I
#90000
0"
0S
#95000
1"
1S
b10 x
#96000
0$
1%
b0 &
0U
1V
0Z
0Y
0W
#100000
0"
0S
#105000
1"
1S
b1 x
b10110000000000000000000000000000 w
0F
0E
0D
0C
0B
0A
0@
0?
0>
0=
0<
0;
0:
09
08
07
06
05
04
03
02
01
00
0/
0.
0-
0,
0+
1*
1)
0(
1'
#106000
b1 J
b0 K
b10110000000000000000000000000000 L
1M
0N
0P
bz Q
0R
b100 I
#110000
0"
0S
#115000
1"
1S
b0 x
1H
#116000
1$
0%
b10110000000000000000000000000000 &
1U
0V
1Z
1Y
1W
#120000
0"
0S
#125000
1"
1S
b1 x
0H
#126000
b1 K
b10110000000000000000000000000001 L
b101 I
#130000
0"
0S
#135000
1"
1S
b10 x
#136000
b10110000000000000000000000000001 &
1v
#140000
0"
0S
#145000
1"
1S
b11 x
#146000
b10 K
b10110000000000000000000000000010 L
b110 I
#150000
0"
0S
#155000
1"
1S
b100 x
#156000
b10110000000000000000000000000010 &
0v
1u
#160000
0"
0S
#165000
1"
1S
b101 x
#166000
b11 K
b10110000000000000000000000000011 L
b111 I
#170000
0"
0S
#175000
1"
1S
b110 x
#176000
b10110000000000000000000000000011 &
1v
#180000
0"
0S
#185000
1"
1S
b111 x
#186000
b100 K
b10110000000000000000000000000100 L
b1000 I
#190000
0"
0S
#195000
1"
1S
b1000 x
#196000
b10110000000000000000000000000100 &
0v
0u
1t
#200000
0"
0S
#205000
1"
1S
b1001 x
#206000
b101 K
b100 K
b0 L
0M
1N
b10110000000000000000000000000100 Q
1R
b1001 I
#210000
0"
0S
#215000
1"
1S
b1010 x
#216000
0$
1%
b0 &
0U
1V
0t
0Z
0Y
0W
#220000
0"
0S
#225000
1"
1S
b1001 x
b10110000000000000000000000000100 w
1D
#226000
b11 K
b10110000000000000000000000000011 Q
b1010 I
#230000
0"
0S
#235000
1"
1S
b1000 x
#240000
0"
0S
#245000
1"
1S
b111 x
b10110000000000000000000000000011 w
1F
1E
0D
#246000
b10 K
b10110000000000000000000000000010 Q
b1011 I
#250000
0"
0S
#255000
1"
1S
b110 x
#260000
0"
0S
#265000
1"
1S
b101 x
b10110000000000000000000000000010 w
0F
#266000
b1 K
b10110000000000000000000000000001 Q
b1100 I
#270000
0"
0S
#275000
1"
1S
b100 x
#280000
0"
0S
#285000
1"
1S
b11 x
b10110000000000000000000000000001 w
1F
0E
#286000
b0 K
1P
b10110000000000000000000000000000 Q
b1101 I
#290000
0"
0S
#295000
1"
1S
b10 x
#300000
0"
0S
#305000
1"
1S
b1 x
b10110000000000000000000000000000 w
0F
#306000
b10 J
b11111111111111111111111111111111 K
b0 K
b10110000000000000000000000000000 L
1M
0N
0P
bz Q
0R
b1110 I
#310000
0"
0S
#315000
1"
1S
b0 x
1H
#316000
1$
0%
b10110000000000000000000000000000 &
1U
0V
1Z
1Y
1W
#320000
0"
0S
#325000
1"
1S
b1 x
0H
#326000
b1 K
b10110000000000000000000000000001 L
b1111 I
#330000
0"
0S
#335000
1"
1S
b10 x
#336000
b10110000000000000000000000000001 &
1v
#340000
0"
0S
#345000
1"
1S
b11 x
#346000
b10 K
b10110000000000000000000000000010 L
b10000 I
#350000
0"
0S
#355000
1"
1S
b100 x
#356000
b10110000000000000000000000000010 &
0v
1u
#360000
0"
0S
#365000
1"
1S
b101 x
#366000
b11 K
b10110000000000000000000000000011 L
b10001 I
#370000
0"
0S
#375000
1"
1S
b110 x
#376000
b10110000000000000000000000000011 &
1v
#380000
0"
0S
#385000
1"
1S
b111 x
#386000
b100 K
b10110000000000000000000000000100 L
b10010 I
#390000
0"
0S
#395000
1"
1S
b1000 x
#396000
b10110000000000000000000000000100 &
0v
0u
1t
#400000
0"
0S
#405000
1"
1S
b1001 x
#406000
b101 K
b10110000000000000000000000000101 L
b10011 I
#410000
0"
0S
#415000
1"
1S
b1010 x
#416000
b10110000000000000000000000000101 &
1v
#420000
0"
0S
#425000
1"
1S
b1011 x
#426000
b110 K
b10110000000000000000000000000110 L
b10100 I
#430000
0"
0S
#435000
1"
1S
b1100 x
#436000
b10110000000000000000000000000110 &
0v
1u
#440000
0"
0S
#445000
1"
1S
b1101 x
#446000
b111 K
b10110000000000000000000000000111 L
b10101 I
#450000
0"
0S
#455000
1"
1S
b1110 x
#456000
b10110000000000000000000000000111 &
1v
#460000
0"
0S
#465000
1"
1S
b1111 x
#466000
b1000 K
b10110000000000000000000000001000 L
b10110 I
#470000
0"
0S
#475000
1"
1S
b10000 x
#476000
b10110000000000000000000000001000 &
0v
0u
0t
1s
#480000
0"
0S
#485000
1"
1S
b10001 x
#486000
b1001 K
b10110000000000000000000000001001 L
b10111 I
#490000
0"
0S
#495000
1"
1S
b10010 x
#496000
b10110000000000000000000000001001 &
1v
#500000
0"
0S
#505000
1"
1S
b10011 x
#506000
b1010 K
b10110000000000000000000000001010 L
b11000 I
#510000
0"
0S
#515000
1"
1S
b10100 x
#516000
b10110000000000000000000000001010 &
0v
1u
#520000
0"
0S
#525000
1"
1S
b10101 x
#526000
b1011 K
b10110000000000000000000000001011 L
b11001 I
#530000
0"
0S
#535000
1"
1S
b10110 x
#536000
b10110000000000000000000000001011 &
1v
#540000
0"
0S
#545000
1"
1S
b10111 x
#546000
b1100 K
b10110000000000000000000000001100 L
b11010 I
#550000
0"
0S
#555000
1"
1S
b11000 x
#556000
b10110000000000000000000000001100 &
0v
0u
1t
#560000
0"
0S
#565000
1"
1S
b11001 x
#566000
b1101 K
b10110000000000000000000000001101 L
b11011 I
#570000
0"
0S
#575000
1"
1S
b11010 x
#576000
b10110000000000000000000000001101 &
1v
#580000
0"
0S
#585000
1"
1S
b11011 x
#586000
b1110 K
b10110000000000000000000000001110 L
b11100 I
#590000
0"
0S
#595000
1"
1S
b11100 x
#596000
b10110000000000000000000000001110 &
0v
1u
#600000
0"
0S
#605000
1"
1S
b11101 x
#606000
b1111 K
b10110000000000000000000000001111 L
b11101 I
#610000
0"
0S
#615000
1"
1S
b11110 x
#616000
b10110000000000000000000000001111 &
1v
#620000
0"
0S
#625000
1"
1S
b11111 x
#626000
b10000 K
b10110000000000000000000000010000 L
b11110 I
#630000
0"
0S
#635000
1"
1S
b100000 x
1G
#636000
b10110000000000000000000000010000 &
0v
0u
0t
0s
1r
#640000
0"
0S
#645000
1"
1S
#646000
b11 J
b10001 K
b10110000000000000000000000010001 L
b11111 I
#650000
0"
0S
#655000
1"
1S
#656000
b10110000000000000000000000010001 &
1v
#660000
0"
0S
#665000
1"
1S
#666000
b100 J
b10010 K
b10110000000000000000000000010010 L
b100000 I
#670000
0"
0S
#675000
1"
1S
#676000
b10110000000000000000000000010010 &
0v
1u
#680000
0"
0S
#685000
1"
1S
#686000
b101 J
b10011 K
b10110000000000000000000000010011 L
b100001 I
#690000
0"
0S
#695000
1"
1S
#696000
b10110000000000000000000000010011 &
1v
#700000
0"
0S
#705000
1"
1S
#706000
b110 J
b10100 K
b10110000000000000000000000010100 L
b100010 I
#710000
0"
0S
#715000
1"
1S
#716000
b10110000000000000000000000010100 &
0v
0u
1t
#720000
0"
0S
#725000
1"
1S
#726000
b111 J
b10101 K
b10110000000000000000000000010101 L
b100011 I
#730000
0"
0S
#735000
1"
1S
#736000
b10110000000000000000000000010101 &
1v
#740000
0"
0S
#745000
1"
1S
#746000
b1000 J
b10110 K
b10110000000000000000000000010110 L
b100100 I
#750000
0"
0S
#755000
1"
1S
#756000
b10110000000000000000000000010110 &
0v
1u
#760000
0"
0S
#765000
1"
1S
#766000
b1001 J
b10111 K
b10110000000000000000000000010111 L
b100101 I
#770000
0"
0S
#775000
1"
1S
#776000
b10110000000000000000000000010111 &
1v
#780000
0"
0S
#785000
1"
1S
#786000
b1010 J
b11000 K
b10110000000000000000000000011000 L
b100110 I
#790000
0"
0S
#795000
1"
1S
#796000
b10110000000000000000000000011000 &
0v
0u
0t
1s
#800000
0"
0S
#805000
1"
1S
#806000
b1011 J
b11001 K
b10110000000000000000000000011001 L
b100111 I
#810000
0"
0S
#815000
1"
1S
#816000
b10110000000000000000000000011001 &
1v
#820000
0"
0S
#825000
1"
1S
#826000
b1100 J
b11010 K
b10110000000000000000000000011010 L
b101000 I
#830000
0"
0S
#835000
1"
1S
#836000
b10110000000000000000000000011010 &
0v
1u
#840000
0"
0S
#845000
1"
1S
#846000
b1101 J
b11011 K
b10110000000000000000000000011011 L
b101001 I
#850000
0"
0S
#855000
1"
1S
#856000
b10110000000000000000000000011011 &
1v
#860000
0"
0S
#865000
1"
1S
#866000
b1110 J
b11100 K
b10110000000000000000000000011100 L
b101010 I
#870000
0"
0S
#875000
1"
1S
#876000
b10110000000000000000000000011100 &
0v
0u
1t
#880000
0"
0S
#885000
1"
1S
#886000
b1111 J
b11101 K
b10110000000000000000000000011101 L
b101011 I
#890000
0"
0S
#895000
1"
1S
#896000
b10110000000000000000000000011101 &
1v
#900000
0"
0S
#905000
1"
1S
#906000
b10000 J
b11110 K
b10110000000000000000000000011110 L
b101100 I
#910000
0"
0S
#915000
1"
1S
#916000
b10110000000000000000000000011110 &
0v
1u
#920000
0"
0S
#925000
1"
1S
#926000
b10001 J
b11111 K
b10110000000000000000000000011111 L
1O
b101101 I
#930000
0"
0S
#935000
1"
1S
#936000
b10110000000000000000000000011111 &
1v
#940000
0"
0S
#945000
1"
1S
#946000
b100000 K
b11111111111111111111111111111111 L
b101110 I
#950000
0"
0S
#955000
1"
1S
#956000
b11111111111111111111111111111111 &
1q
1p
1o
1n
1m
1l
1k
1j
1i
1h
1g
1f
1e
1d
1c
1b
1a
1`
1_
1^
1]
1\
1[
1X
#960000
0"
0S
#965000
1"
1S
#966000
b11111 K
b0 L
0M
1N
0O
b10110000000000000000000000011111 Q
1R
b101111 I
#970000
0"
0S
#975000
1"
1S
#976000
0$
1%
b0 &
0U
1V
0v
0u
0t
0s
0r
0q
0p
0o
0n
0m
0l
0k
0j
0i
0h
0g
0f
0e
0d
0c
0b
0a
0`
0_
0^
0]
0\
0[
0Z
0Y
0X
0W
#980000
0"
0S
#985000
1"
1S
b11111 x
b10110000000000000000000000001111 w
0G
1F
1E
1D
1C
#986000
b10010 J
b11110 K
b10110000000000000000000000011110 Q
b110000 I
#990000
0"
0S
#995000
1"
1S
b11110 x
#1000000
0"
0S
#1005000
1"
1S
b11101 x
b10110000000000000000000000001110 w
0F
#1006000
b10011 J
b11101 K
b10110000000000000000000000011101 Q
b110001 I
#1010000
0"
0S
#1015000
1"
1S
b11100 x
#1020000
0"
0S
#1025000
1"
1S
b11011 x
b10110000000000000000000000001101 w
1F
0E
#1026000
b10100 J
b11100 K
b10110000000000000000000000011100 Q
b110010 I
#1030000
0"
0S
#1035000
1"
1S
b11010 x
#1040000
0"
0S
#1045000
1"
1S
b11001 x
b10110000000000000000000000001100 w
0F
#1046000
b10101 J
b11011 K
b10110000000000000000000000011011 Q
b110011 I
#1050000
0"
0S
#1055000
1"
1S
b11000 x
#1060000
0"
0S
#1065000
1"
1S
b10111 x
b10110000000000000000000000001011 w
1F
1E
0D
#1066000
b10110 J
b11010 K
b10110000000000000000000000011010 Q
b110100 I
#1070000
0"
0S
#1075000
1"
1S
b10110 x
#1080000
0"
0S
#1085000
1"
1S
b10101 x
b10110000000000000000000000001010 w
0F
#1086000
b10111 J
b11001 K
b10110000000000000000000000011001 Q
b110101 I
#1090000
0"
0S
#1095000
1"
1S
b10100 x
#1100000
0"
0S
#1105000
1"
1S
b10011 x
b10110000000000000000000000001001 w
1F
0E
#1106000
b11000 J
b11000 K
b10110000000000000000000000011000 Q
b110110 I
#1110000
0"
0S
#1115000
1"
1S
b10010 x
#1120000
0"
0S
#1125000
1"
1S
b10001 x
b10110000000000000000000000001000 w
0F
#1126000
b11001 J
b10111 K
b10110000000000000000000000010111 Q
b110111 I
#1130000
0"
0S
#1135000
1"
1S
b10000 x
#1140000
0"
0S
#1145000
1"
1S
b1111 x
b10110000000000000000000000000111 w
1F
1E
1D
0C
#1146000
b11010 J
b10110 K
b10110000000000000000000000010110 Q
b111000 I
#1150000
0"
0S
#1155000
1"
1S
b1110 x
#1160000
0"
0S
#1165000
1"
1S
b1101 x
b10110000000000000000000000000110 w
0F
#1166000
b11011 J
b10101 K
b10110000000000000000000000010101 Q
b111001 I
#1170000
0"
0S
#1175000
1"
1S
b1100 x
#1180000
0"
0S
#1185000
1"
1S
b1011 x
b10110000000000000000000000000101 w
1F
0E
#1186000
b11100 J
b10100 K
b10110000000000000000000000010100 Q
b111010 I
#1190000
0"
0S
#1195000
1"
1S
b1010 x
#1200000
0"
0S
#1205000
1"
1S
b1001 x
b10110000000000000000000000000100 w
0F
#1206000
b11101 J
b10011 K
b10110000000000000000000000010011 Q
b111011 I
#1210000
0"
0S
#1215000
1"
1S
b1000 x
#1220000
0"
0S
#1225000
1"
1S
b111 x
b10110000000000000000000000000011 w
1F
1E
0D
#1226000
b11110 J
b10010 K
b10110000000000000000000000010010 Q
b111100 I
#1230000
0"
0S
#1235000
1"
1S
b110 x
#1240000
0"
0S
#1245000
1"
1S
b101 x
b10110000000000000000000000000010 w
0F
#1246000
b11111 J
b10001 K
b10110000000000000000000000010001 Q
b111101 I
#1250000
0"
0S
#1255000
1"
1S
b100 x
#1260000
0"
0S
#1265000
1"
1S
b11 x
b10110000000000000000000000000001 w
1F
0E
#1266000
b100000 J
b10000 K
b10110000000000000000000000010000 Q
b111110 I
#1270000
0"
0S
#1275000
1"
1S
b10 x
#1280000
0"
0S
#1285000
1"
1S
b1 x
b10110000000000000000000000000000 w
0F
#1286000
b100001 J
b1111 K
b10110000000000000000000000001111 Q
b111111 I
#1290000
0"
0S
#1295000
1"
1S
b0 x
1H
#1300000
0"
0S
#1305000
1"
1S
#1306000
b100010 J
b100011 J
b1110 K
b10110000000000000000000000001110 Q
b1000000 I
#1310000
0"
0S
#1315000
1"
1S
#1320000
0"
0S
#1325000
1"
1S
#1326000
b100100 J
b100101 J
b1101 K
b10110000000000000000000000001101 Q
b1000001 I
#1330000
0"
0S
#1335000
1"
1S
#1340000
0"
0S
#1345000
1"
1S
#1346000
b100110 J
b100111 J
b1100 K
b10110000000000000000000000001100 Q
b1000010 I
#1350000
0"
0S
#1355000
1"
1S
#1360000
0"
0S
#1365000
1"
1S
#1366000
b101000 J
b101001 J
b1011 K
b10110000000000000000000000001011 Q
b1000011 I
#1370000
0"
0S
#1375000
1"
1S
#1380000
0"
0S
#1385000
1"
1S
#1386000
b101010 J
b101011 J
b1010 K
b10110000000000000000000000001010 Q
b1000100 I
#1390000
0"
0S
#1395000
1"
1S
#1400000
0"
0S
#1405000
1"
1S
#1406000
b101100 J
b101101 J
b1001 K
b10110000000000000000000000001001 Q
b1000101 I
#1410000
0"
0S
#1415000
1"
1S
#1420000
0"
0S
#1425000
1"
1S
#1426000
b101110 J
b101111 J
b1000 K
b10110000000000000000000000001000 Q
b1000110 I
#1430000
0"
0S
#1435000
1"
1S
#1440000
0"
0S
#1445000
1"
1S
#1446000
b110000 J
b110001 J
b111 K
b10110000000000000000000000000111 Q
b1000111 I
#1450000
0"
0S
#1455000
1"
1S
#1460000
0"
0S
#1465000
1"
1S
#1466000
b110010 J
b110011 J
b110 K
b10110000000000000000000000000110 Q
b1001000 I
#1470000
0"
0S
#1475000
1"
1S
#1480000
0"
0S
#1485000
1"
1S
#1486000
b110100 J
b110101 J
b101 K
b10110000000000000000000000000101 Q
b1001001 I
#1490000
0"
0S
#1495000
1"
1S
#1500000
0"
0S
#1505000
1"
1S
#1506000
b110110 J
b110111 J
b100 K
b10110000000000000000000000000100 Q
b1001010 I
#1510000
0"
0S
#1515000
1"
1S
#1520000
0"
0S
#1525000
1"
1S
#1526000
b111000 J
b111001 J
b11 K
b10110000000000000000000000000011 Q
b1001011 I
#1530000
0"
0S
#1535000
1"
1S
#1540000
0"
0S
#1545000
1"
1S
#1546000
b111010 J
b111011 J
b10 K
b10110000000000000000000000000010 Q
b1001100 I
#1550000
0"
0S
#1555000
1"
1S
#1560000
0"
0S
#1565000
1"
1S
#1566000
b111100 J
b111101 J
b1 K
b10110000000000000000000000000001 Q
b1001101 I
#1570000
0"
0S
#1575000
1"
1S
#1580000
0"
0S
#1585000
1"
1S
#1586000
b111110 J
b111111 J
b0 K
1P
b10110000000000000000000000000000 Q
b1001110 I
#1590000
0"
0S
#1595000
1"
1S
#1600000
0"
0S
#1605000
1"
1S
#1606000
b11111111111111111111111111111111 K
bz Q
0R
b1001111 I
#1610000
0"
0S
#1615000
1"
1S
#1620000
0"
0S
#1625000
1"
1S
#1626000
b0 K
b10110000000000000000000000000000 L
1M
0N
0P
b1010000 I
#1630000
0"
0S
#1635000
1"
1S
#1636000
1$
0%
b10110000000000000000000000000000 &
1U
0V
1Z
1Y
1W
#1640000
0"
0S
#1645000
1"
1S
b1 x
0H
#1646000
b1 K
b10110000000000000000000000000001 L
b1010001 I
#1650000
0"
0S
#1655000
1"
1S
b10 x
#1656000
b10110000000000000000000000000001 &
1v
#1660000
0"
0S
#1665000
1"
1S
b11 x
#1666000
b10 K
b10110000000000000000000000000010 L
b1010010 I
#1670000
0"
0S
#1675000
1"
1S
b100 x
#1676000
b10110000000000000000000000000010 &
0v
1u
#1680000
0"
0S
#1685000
1"
1S
b101 x
#1686000
b11 K
b10110000000000000000000000001010 L
1N
b1010011 I
#1690000
0"
0S
#1695000
1"
1S
b110 x
#1696000
1%
b10110000000000000000000000001010 &
1V
1s
#1700000
0"
0S
#1705000
1"
1S
b111 x
#1706000
b0 L
0M
b10110000000000000000000000001010 Q
1R
b1010100 I
#1710000
0"
0S
#1715000
1"
1S
b1000 x
#1716000
0$
b0 &
0U
0u
0s
0Z
0Y
0W
#1720000
0"
0S
#1725000
1"
1S
b111 x
b10110000000000000000000000001010 w
1E
1C
#1726000
b10 K
b10110000000000000000000000000010 Q
b1010101 I
#1730000
0"
0S
#1735000
1"
1S
b110 x
#1740000
0"
0S
#1745000
1"
1S
b101 x
b10110000000000000000000000000010 w
0C
#1746000
b1 K
b10110000000000000000000000000001 Q
b1010110 I
#1750000
0"
0S
#1755000
1"
1S
b100 x
#1760000
0"
0S
#1765000
1"
1S
b11 x
b10110000000000000000000000000001 w
1F
0E
#1766000
b0 K
1P
b10110000000000000000000000000000 Q
b1010111 I
#1770000
0"
0S
#1775000
1"
1S
b10 x
#1780000
0"
0S
#1785000
1"
1S
b1 x
b10110000000000000000000000000000 w
0F
#1786000
b1000000 J
b11111111111111111111111111111111 K
#1790000
0"
0S
#1795000
1"
1S
b0 x
1H
